nlp_exp/__init__.py
nlp_exp/operations.py
nlp_lab_final-0.1.dist-info/METADATA
nlp_lab_final-0.1.dist-info/WHEEL
nlp_lab_final-0.1.dist-info/top_level.txt
nlp_lab_final-0.1.dist-info/RECORD
