Metadata-Version: 2.1
Name: nlp-lab-final
Version: 0.1
Summary: A custom NLP package
Author: Your Name
